id801/__init__.py
id801/id801.py
id801/id801_client.py
id801/id801_publisher.py
id801/id801_server.py
id801/id801_subscriber.py
idq_id801-1.0.2.dist-info/LICENSE.txt
idq_id801-1.0.2.dist-info/METADATA
idq_id801-1.0.2.dist-info/WHEEL
idq_id801-1.0.2.dist-info/top_level.txt
idq_id801-1.0.2.dist-info/RECORD
