Metadata-Version: 2.1
Name: idq-id801
Version: 1.0.2
Summary: Python library for interfacing with IDQ ID801 Time to Digital Converter
Home-page: https://github.com/NextZtepS/idq_id801_tdc
Author: NextZtepS
Author-email: natdanaiongarjvaja@gmail.com
License: MIT
License-File: LICENSE.txt
Requires-Dist: numpy
Requires-Dist: pandas
Requires-Dist: matplotlib
Provides-Extra: dev
Requires-Dist: pytest; extra == "dev"
Requires-Dist: twine; extra == "dev"
